<?xml version="1.0"?>
<org.cidrz.webapp.dynasite.valueobject.Form>
  <id>9</id>
  <name>labResults</name>
  <label>Laboratory Results</label>
  <requireReauth>true</requireReauth>
  <requirePatient>true</requirePatient>
  <enabled>true</enabled>
  <ruleDefinitions/>
  <flow>
    <id>102</id>
    <name>Lab</name>
    <flowOrder>102</flowOrder>
    <forms class="tree-set">
      <comparator class="org.cidrz.webapp.dynasite.utils.sort.FlowOrderComparator"/>
    </forms>
  </flow>
  <flowId>102</flowId>
  <flowOrder>0</flowOrder>
  <formType>
    <id>4</id>
    <name>Mother and Infant</name>
  </formType>
  <formTypeId>4</formTypeId>
  <pageItems class="tree-set">
    <comparator class="org.cidrz.webapp.dynasite.utils.sort.DisplayOrderComparator"/>
    <org.cidrz.webapp.dynasite.valueobject.PageItem>
      <id>2800</id>
      <form__field>
        <id>1427</id>
        <label>BEGIN TABLE</label>
        <type>Display</type>
        <required>false</required>
        <minValue>0</minValue>
        <maxValue>0</maxValue>
        <units></units>
        <displayOrder>2147483647</displayOrder>
        <patientProperty></patientProperty>
        <isEnabled>true</isEnabled>
        <ruleDefinitions/>
        <enumerations/>
        <shared>true</shared>
        <starSchemaName></starSchemaName>
        <encounterRecordproperty></encounterRecordproperty>
        <patientStatusproperty></patientStatusproperty>
      </form__field>
      <formFieldId>1427</formFieldId>
      <displayOrder>0</displayOrder>
      <inputType>display-tbl-begin</inputType>
      <closeRow>false</closeRow>
      <columnNumber>0</columnNumber>
      <size>0</size>
      <maxlength>0</maxlength>
      <rows>0</rows>
      <cols>2</cols>
      <visible>true</visible>
      <formId>9</formId>
      <colspan>0</colspan>
      <highlightCell>false</highlightCell>
    </org.cidrz.webapp.dynasite.valueobject.PageItem>
    <org.cidrz.webapp.dynasite.valueobject.PageItem>
      <id>1419</id>
      <form__field>
        <id>193</id>
        <label>ABO Group</label>
        <type>Enum</type>
        <required>false</required>
        <minValue>0</minValue>
        <maxValue>0</maxValue>
        <units></units>
        <displayOrder>2147483647</displayOrder>
        <patientProperty></patientProperty>
        <isEnabled>true</isEnabled>
        <ruleDefinitions/>
        <enumerations class="tree-set">
          <comparator class="org.cidrz.webapp.dynasite.utils.sort.DisplayOrderComparator"/>
          <org.cidrz.webapp.dynasite.valueobject.FieldEnumeration>
            <id>103</id>
            <fieldId>193</fieldId>
            <enumeration>A</enumeration>
            <numericValue>0</numericValue>
            <enabled>true</enabled>
            <concatEnumNumeric>A (0)</concatEnumNumeric>
            <displayOrder>0</displayOrder>
          </org.cidrz.webapp.dynasite.valueobject.FieldEnumeration>
          <org.cidrz.webapp.dynasite.valueobject.FieldEnumeration>
            <id>635</id>
            <fieldId>193</fieldId>
            <enumeration>B</enumeration>
            <numericValue>1</numericValue>
            <enabled>true</enabled>
            <concatEnumNumeric>B (1)</concatEnumNumeric>
            <displayOrder>1</displayOrder>
          </org.cidrz.webapp.dynasite.valueobject.FieldEnumeration>
          <org.cidrz.webapp.dynasite.valueobject.FieldEnumeration>
            <id>1114</id>
            <fieldId>193</fieldId>
            <enumeration>AB</enumeration>
            <numericValue>2</numericValue>
            <enabled>true</enabled>
            <concatEnumNumeric>AB (2)</concatEnumNumeric>
            <displayOrder>2</displayOrder>
          </org.cidrz.webapp.dynasite.valueobject.FieldEnumeration>
          <org.cidrz.webapp.dynasite.valueobject.FieldEnumeration>
            <id>1436</id>
            <fieldId>193</fieldId>
            <enumeration>O</enumeration>
            <numericValue>3</numericValue>
            <enabled>true</enabled>
            <concatEnumNumeric>O (3)</concatEnumNumeric>
            <displayOrder>3</displayOrder>
          </org.cidrz.webapp.dynasite.valueobject.FieldEnumeration>
          <org.cidrz.webapp.dynasite.valueobject.FieldEnumeration>
            <id>1664</id>
            <fieldId>193</fieldId>
            <enumeration>Not Done</enumeration>
            <numericValue>4</numericValue>
            <enabled>true</enabled>
            <concatEnumNumeric>Not Done (4)</concatEnumNumeric>
            <displayOrder>4</displayOrder>
          </org.cidrz.webapp.dynasite.valueobject.FieldEnumeration>
        </enumerations>
        <shared>true</shared>
        <starSchemaName>abo_group_193</starSchemaName>
        <encounterRecordproperty></encounterRecordproperty>
        <patientStatusproperty></patientStatusproperty>
      </form__field>
      <formFieldId>193</formFieldId>
      <displayOrder>1</displayOrder>
      <inputType>select</inputType>
      <closeRow>true</closeRow>
      <columnNumber>0</columnNumber>
      <size>0</size>
      <maxlength>0</maxlength>
      <rows>0</rows>
      <cols>0</cols>
      <visible>true</visible>
      <visibleEnumIdTrigger1>1664</visibleEnumIdTrigger1>
      <visibleDependencies1>194</visibleDependencies1>
      <visibleEnumIdTrigger2>-1</visibleEnumIdTrigger2>
      <selectedEnum>-1</selectedEnum>
      <visibleDependencies2></visibleDependencies2>
      <formId>9</formId>
      <colspan>2</colspan>
      <dempMap1>
        <entry>
          <string>194</string>
          <long>1419</long>
        </entry>
      </dempMap1>
      <highlightCell>false</highlightCell>
    </org.cidrz.webapp.dynasite.valueobject.PageItem>
    <org.cidrz.webapp.dynasite.valueobject.PageItem>
      <id>1420</id>
      <form__field>
        <id>194</id>
        <label>If ABO Group not done, Reason</label>
        <type>Enum</type>
        <required>false</required>
        <minValue>0</minValue>
        <maxValue>0</maxValue>
        <units></units>
        <displayOrder>1</displayOrder>
        <patientProperty></patientProperty>
        <isEnabled>true</isEnabled>
        <ruleDefinitions/>
        <enumerations class="tree-set">
          <comparator class="org.cidrz.webapp.dynasite.utils.sort.DisplayOrderComparator"/>
          <org.cidrz.webapp.dynasite.valueobject.FieldEnumeration>
            <id>104</id>
            <fieldId>194</fieldId>
            <enumeration>No Reagents</enumeration>
            <enabled>true</enabled>
            <displayOrder>0</displayOrder>
          </org.cidrz.webapp.dynasite.valueobject.FieldEnumeration>
          <org.cidrz.webapp.dynasite.valueobject.FieldEnumeration>
            <id>636</id>
            <fieldId>194</fieldId>
            <enumeration>Other, Describe</enumeration>
            <enabled>true</enabled>
            <displayOrder>1</displayOrder>
          </org.cidrz.webapp.dynasite.valueobject.FieldEnumeration>
        </enumerations>
        <shared>false</shared>
        <starSchemaName>no_abo_group_reason_194</starSchemaName>
        <encounterRecordproperty></encounterRecordproperty>
        <patientStatusproperty></patientStatusproperty>
        <patientLabproperty></patientLabproperty>
      </form__field>
      <formFieldId>194</formFieldId>
      <displayOrder>2</displayOrder>
      <inputType>select</inputType>
      <closeRow>false</closeRow>
      <size>0</size>
      <maxlength>0</maxlength>
      <rows>0</rows>
      <cols>0</cols>
      <visible>false</visible>
      <visibleEnumIdTrigger1>636</visibleEnumIdTrigger1>
      <visibleDependencies1>195</visibleDependencies1>
      <formId>9</formId>
      <dempMap1>
        <entry>
          <string>195</string>
          <long>1420</long>
        </entry>
      </dempMap1>
      <highlightCell>false</highlightCell>
    </org.cidrz.webapp.dynasite.valueobject.PageItem>
    <org.cidrz.webapp.dynasite.valueobject.PageItem>
      <id>1421</id>
      <form__field>
        <id>195</id>
        <label>If ABO Group not done, Reason, Describe</label>
        <type>Text</type>
        <required>false</required>
        <minValue>0</minValue>
        <maxValue>0</maxValue>
        <units></units>
        <displayOrder>2</displayOrder>
        <patientProperty></patientProperty>
        <isEnabled>true</isEnabled>
        <ruleDefinitions/>
        <enumerations/>
        <shared>false</shared>
        <starSchemaName>no_abo_group_reason_desc_195</starSchemaName>
        <encounterRecordproperty></encounterRecordproperty>
        <patientStatusproperty></patientStatusproperty>
        <patientLabproperty></patientLabproperty>
      </form__field>
      <formFieldId>195</formFieldId>
      <displayOrder>3</displayOrder>
      <inputType>textarea</inputType>
      <closeRow>false</closeRow>
      <size>0</size>
      <maxlength>0</maxlength>
      <rows>0</rows>
      <cols>0</cols>
      <visible>false</visible>
      <visibleDependencies1></visibleDependencies1>
      <formId>9</formId>
      <highlightCell>false</highlightCell>
    </org.cidrz.webapp.dynasite.valueobject.PageItem>
    <org.cidrz.webapp.dynasite.valueobject.PageItem>
      <id>1422</id>
      <form__field>
        <id>196</id>
        <label>Rhesus</label>
        <type>Enum</type>
        <required>false</required>
        <minValue>0</minValue>
        <maxValue>0</maxValue>
        <units></units>
        <displayOrder>2147483647</displayOrder>
        <patientProperty></patientProperty>
        <isEnabled>true</isEnabled>
        <ruleDefinitions>
          <org.cidrz.webapp.dynasite.valueobject.RuleDefinition>
            <id>27</id>
            <ruleClass>org.cidrz.webapp.dynasite.rules.impl.SimpleComparison</ruleClass>
            <outcomeClass>org.cidrz.webapp.dynasite.rules.impl.InfoOutcome</outcomeClass>
            <fieldId>196</fieldId>
            <enabled>true</enabled>
            <ruleParams/>
            <outcomeParams/>
            <message>Rh- Lab Result</message>
            <operand>0</operand>
            <operator>eq</operator>
            <allPregnancies>false</allPregnancies>
          </org.cidrz.webapp.dynasite.valueobject.RuleDefinition>
        </ruleDefinitions>
        <enumerations class="tree-set">
          <comparator class="org.cidrz.webapp.dynasite.utils.sort.DisplayOrderComparator"/>
          <org.cidrz.webapp.dynasite.valueobject.FieldEnumeration>
            <id>105</id>
            <fieldId>196</fieldId>
            <enumeration>Rh- (Negative)</enumeration>
            <numericValue>5</numericValue>
            <enabled>true</enabled>
            <concatEnumNumeric>Rh- (Negative) (5)</concatEnumNumeric>
            <displayOrder>0</displayOrder>
          </org.cidrz.webapp.dynasite.valueobject.FieldEnumeration>
          <org.cidrz.webapp.dynasite.valueobject.FieldEnumeration>
            <id>637</id>
            <fieldId>196</fieldId>
            <enumeration>Rh+ (Positive)</enumeration>
            <numericValue>6</numericValue>
            <enabled>true</enabled>
            <concatEnumNumeric>Rh+ (Positive) (6)</concatEnumNumeric>
            <displayOrder>1</displayOrder>
          </org.cidrz.webapp.dynasite.valueobject.FieldEnumeration>
          <org.cidrz.webapp.dynasite.valueobject.FieldEnumeration>
            <id>1115</id>
            <fieldId>196</fieldId>
            <enumeration>Not Done</enumeration>
            <numericValue>4</numericValue>
            <enabled>true</enabled>
            <concatEnumNumeric>Not Done (4)</concatEnumNumeric>
            <displayOrder>2</displayOrder>
          </org.cidrz.webapp.dynasite.valueobject.FieldEnumeration>
        </enumerations>
        <shared>true</shared>
        <starSchemaName>rhesus_196</starSchemaName>
        <encounterRecordproperty></encounterRecordproperty>
        <patientStatusproperty></patientStatusproperty>
      </form__field>
      <formFieldId>196</formFieldId>
      <displayOrder>4</displayOrder>
      <inputType>select</inputType>
      <closeRow>true</closeRow>
      <columnNumber>0</columnNumber>
      <size>0</size>
      <maxlength>0</maxlength>
      <rows>0</rows>
      <cols>0</cols>
      <visible>true</visible>
      <visibleEnumIdTrigger1>1115</visibleEnumIdTrigger1>
      <visibleDependencies1>197</visibleDependencies1>
      <visibleEnumIdTrigger2>-1</visibleEnumIdTrigger2>
      <selectedEnum>-1</selectedEnum>
      <visibleDependencies2></visibleDependencies2>
      <formId>9</formId>
      <colspan>2</colspan>
      <dempMap1>
        <entry>
          <string>197</string>
          <long>1422</long>
        </entry>
      </dempMap1>
      <highlightCell>false</highlightCell>
    </org.cidrz.webapp.dynasite.valueobject.PageItem>
    <org.cidrz.webapp.dynasite.valueobject.PageItem>
      <id>1423</id>
      <form__field>
        <id>197</id>
        <label>If Rhesus not done, Reason</label>
        <type>Enum</type>
        <required>false</required>
        <minValue>0</minValue>
        <maxValue>0</maxValue>
        <units></units>
        <displayOrder>4</displayOrder>
        <patientProperty></patientProperty>
        <isEnabled>true</isEnabled>
        <ruleDefinitions/>
        <enumerations class="tree-set">
          <comparator class="org.cidrz.webapp.dynasite.utils.sort.DisplayOrderComparator"/>
          <org.cidrz.webapp.dynasite.valueobject.FieldEnumeration>
            <id>106</id>
            <fieldId>197</fieldId>
            <enumeration>No Reagents</enumeration>
            <enabled>true</enabled>
            <displayOrder>0</displayOrder>
          </org.cidrz.webapp.dynasite.valueobject.FieldEnumeration>
          <org.cidrz.webapp.dynasite.valueobject.FieldEnumeration>
            <id>638</id>
            <fieldId>197</fieldId>
            <enumeration>Other, Describe</enumeration>
            <enabled>true</enabled>
            <displayOrder>1</displayOrder>
          </org.cidrz.webapp.dynasite.valueobject.FieldEnumeration>
        </enumerations>
        <shared>false</shared>
        <starSchemaName>no_rhesus_reason_197</starSchemaName>
        <encounterRecordproperty></encounterRecordproperty>
        <patientStatusproperty></patientStatusproperty>
        <patientLabproperty></patientLabproperty>
      </form__field>
      <formFieldId>197</formFieldId>
      <displayOrder>5</displayOrder>
      <inputType>select</inputType>
      <closeRow>false</closeRow>
      <size>0</size>
      <maxlength>0</maxlength>
      <rows>0</rows>
      <cols>0</cols>
      <visible>false</visible>
      <visibleEnumIdTrigger1>638</visibleEnumIdTrigger1>
      <visibleDependencies1>198</visibleDependencies1>
      <formId>9</formId>
      <dempMap1>
        <entry>
          <string>198</string>
          <long>1423</long>
        </entry>
      </dempMap1>
      <highlightCell>false</highlightCell>
    </org.cidrz.webapp.dynasite.valueobject.PageItem>
    <org.cidrz.webapp.dynasite.valueobject.PageItem>
      <id>1425</id>
      <form__field>
        <id>198</id>
        <label>If Rhesus not done, Reason, Describe</label>
        <type>Text</type>
        <required>false</required>
        <minValue>0</minValue>
        <maxValue>0</maxValue>
        <units></units>
        <displayOrder>5</displayOrder>
        <patientProperty></patientProperty>
        <isEnabled>true</isEnabled>
        <ruleDefinitions/>
        <enumerations/>
        <shared>false</shared>
        <starSchemaName>no_rhesus_reason_desc_198</starSchemaName>
        <encounterRecordproperty></encounterRecordproperty>
        <patientStatusproperty></patientStatusproperty>
        <patientLabproperty></patientLabproperty>
      </form__field>
      <formFieldId>198</formFieldId>
      <displayOrder>6</displayOrder>
      <inputType>textarea</inputType>
      <closeRow>false</closeRow>
      <size>0</size>
      <maxlength>0</maxlength>
      <rows>0</rows>
      <cols>0</cols>
      <visible>false</visible>
      <visibleDependencies1></visibleDependencies1>
      <formId>9</formId>
      <highlightCell>false</highlightCell>
    </org.cidrz.webapp.dynasite.valueobject.PageItem>
    <org.cidrz.webapp.dynasite.valueobject.PageItem>
      <id>1426</id>
      <form__field>
        <id>199</id>
        <label>RPR Result</label>
        <type>Enum</type>
        <required>false</required>
        <minValue>0</minValue>
        <maxValue>0</maxValue>
        <units></units>
        <displayOrder>2147483647</displayOrder>
        <patientProperty></patientProperty>
        <isEnabled>true</isEnabled>
        <ruleDefinitions>
          <org.cidrz.webapp.dynasite.valueobject.RuleDefinition>
            <id>28</id>
            <ruleClass>org.cidrz.webapp.dynasite.rules.impl.SimpleComparison</ruleClass>
            <outcomeClass>org.cidrz.webapp.dynasite.rules.impl.InfoOutcome</outcomeClass>
            <fieldId>199</fieldId>
            <enabled>true</enabled>
            <ruleParams/>
            <outcomeParams/>
            <message>RPR Result: Reactive (positive)</message>
            <operand>1</operand>
            <operator>eq</operator>
            <allPregnancies>false</allPregnancies>
          </org.cidrz.webapp.dynasite.valueobject.RuleDefinition>
        </ruleDefinitions>
        <enumerations class="tree-set">
          <comparator class="org.cidrz.webapp.dynasite.utils.sort.DisplayOrderComparator"/>
          <org.cidrz.webapp.dynasite.valueobject.FieldEnumeration>
            <id>107</id>
            <fieldId>199</fieldId>
            <enumeration>Non-Reactive (Negative)</enumeration>
            <numericValue>0</numericValue>
            <enabled>true</enabled>
            <concatEnumNumeric>Non-Reactive (Negative) (0)</concatEnumNumeric>
            <displayOrder>0</displayOrder>
          </org.cidrz.webapp.dynasite.valueobject.FieldEnumeration>
          <org.cidrz.webapp.dynasite.valueobject.FieldEnumeration>
            <id>639</id>
            <fieldId>199</fieldId>
            <enumeration>Reactive (Positive)</enumeration>
            <numericValue>1</numericValue>
            <enabled>true</enabled>
            <concatEnumNumeric>Reactive (Positive) (1)</concatEnumNumeric>
            <displayOrder>1</displayOrder>
          </org.cidrz.webapp.dynasite.valueobject.FieldEnumeration>
          <org.cidrz.webapp.dynasite.valueobject.FieldEnumeration>
            <id>1116</id>
            <fieldId>199</fieldId>
            <enumeration>Not Done</enumeration>
            <numericValue>2</numericValue>
            <enabled>true</enabled>
            <concatEnumNumeric>Not Done (2)</concatEnumNumeric>
            <displayOrder>2</displayOrder>
          </org.cidrz.webapp.dynasite.valueobject.FieldEnumeration>
        </enumerations>
        <shared>false</shared>
        <starSchemaName>rpr_result_199</starSchemaName>
        <encounterRecordproperty></encounterRecordproperty>
      </form__field>
      <formFieldId>199</formFieldId>
      <displayOrder>7</displayOrder>
      <inputType>select</inputType>
      <closeRow>true</closeRow>
      <columnNumber>0</columnNumber>
      <size>0</size>
      <maxlength>0</maxlength>
      <rows>0</rows>
      <cols>0</cols>
      <visible>true</visible>
      <visibleEnumIdTrigger1>1116</visibleEnumIdTrigger1>
      <visibleDependencies1>200</visibleDependencies1>
      <formId>9</formId>
      <colspan>2</colspan>
      <dempMap1>
        <entry>
          <string>200</string>
          <long>1426</long>
        </entry>
      </dempMap1>
      <highlightCell>false</highlightCell>
    </org.cidrz.webapp.dynasite.valueobject.PageItem>
    <org.cidrz.webapp.dynasite.valueobject.PageItem>
      <id>1440</id>
      <form__field>
        <id>200</id>
        <label>If RPR not done, Reason</label>
        <type>Enum</type>
        <required>false</required>
        <minValue>0</minValue>
        <maxValue>0</maxValue>
        <units></units>
        <displayOrder>7</displayOrder>
        <patientProperty></patientProperty>
        <isEnabled>true</isEnabled>
        <ruleDefinitions/>
        <enumerations class="tree-set">
          <comparator class="org.cidrz.webapp.dynasite.utils.sort.DisplayOrderComparator"/>
          <org.cidrz.webapp.dynasite.valueobject.FieldEnumeration>
            <id>108</id>
            <fieldId>200</fieldId>
            <enumeration>No Reagents</enumeration>
            <enabled>true</enabled>
            <displayOrder>0</displayOrder>
          </org.cidrz.webapp.dynasite.valueobject.FieldEnumeration>
          <org.cidrz.webapp.dynasite.valueobject.FieldEnumeration>
            <id>640</id>
            <fieldId>200</fieldId>
            <enumeration>Other, Describe</enumeration>
            <enabled>true</enabled>
            <displayOrder>1</displayOrder>
          </org.cidrz.webapp.dynasite.valueobject.FieldEnumeration>
        </enumerations>
        <shared>false</shared>
        <starSchemaName>no_rpr_reason_200</starSchemaName>
        <encounterRecordproperty></encounterRecordproperty>
        <patientStatusproperty></patientStatusproperty>
        <patientLabproperty></patientLabproperty>
      </form__field>
      <formFieldId>200</formFieldId>
      <displayOrder>8</displayOrder>
      <inputType>select</inputType>
      <closeRow>false</closeRow>
      <size>0</size>
      <maxlength>0</maxlength>
      <rows>0</rows>
      <cols>0</cols>
      <visible>false</visible>
      <visibleEnumIdTrigger1>640</visibleEnumIdTrigger1>
      <visibleDependencies1>201</visibleDependencies1>
      <formId>9</formId>
      <dempMap1>
        <entry>
          <string>201</string>
          <long>1440</long>
        </entry>
      </dempMap1>
      <highlightCell>false</highlightCell>
    </org.cidrz.webapp.dynasite.valueobject.PageItem>
    <org.cidrz.webapp.dynasite.valueobject.PageItem>
      <id>1441</id>
      <form__field>
        <id>201</id>
        <label>If RPR not done, Reason, Describe</label>
        <type>Text</type>
        <required>false</required>
        <minValue>0</minValue>
        <maxValue>0</maxValue>
        <units></units>
        <displayOrder>8</displayOrder>
        <patientProperty></patientProperty>
        <isEnabled>true</isEnabled>
        <ruleDefinitions/>
        <enumerations/>
        <shared>false</shared>
        <starSchemaName>no_rpr_reason_desc_201</starSchemaName>
        <encounterRecordproperty></encounterRecordproperty>
        <patientStatusproperty></patientStatusproperty>
        <patientLabproperty></patientLabproperty>
      </form__field>
      <formFieldId>201</formFieldId>
      <displayOrder>9</displayOrder>
      <inputType>textarea</inputType>
      <closeRow>false</closeRow>
      <size>0</size>
      <maxlength>0</maxlength>
      <rows>0</rows>
      <cols>0</cols>
      <visible>false</visible>
      <visibleDependencies1></visibleDependencies1>
      <formId>9</formId>
      <highlightCell>false</highlightCell>
    </org.cidrz.webapp.dynasite.valueobject.PageItem>
    <org.cidrz.webapp.dynasite.valueobject.PageItem>
      <id>1429</id>
      <form__field>
        <id>202</id>
        <label>If Reactive, Treatment</label>
        <type>Enum</type>
        <required>false</required>
        <minValue>0</minValue>
        <maxValue>0</maxValue>
        <units></units>
        <displayOrder>2147483647</displayOrder>
        <patientProperty></patientProperty>
        <isEnabled>true</isEnabled>
        <ruleDefinitions/>
        <enumerations class="tree-set">
          <comparator class="org.cidrz.webapp.dynasite.utils.sort.DisplayOrderComparator"/>
          <org.cidrz.webapp.dynasite.valueobject.FieldEnumeration>
            <id>109</id>
            <fieldId>202</fieldId>
            <enumeration>None</enumeration>
            <enabled>true</enabled>
            <displayOrder>0</displayOrder>
          </org.cidrz.webapp.dynasite.valueobject.FieldEnumeration>
          <org.cidrz.webapp.dynasite.valueobject.FieldEnumeration>
            <id>641</id>
            <fieldId>202</fieldId>
            <enumeration>Penicillin Injection</enumeration>
            <enabled>true</enabled>
            <displayOrder>1</displayOrder>
          </org.cidrz.webapp.dynasite.valueobject.FieldEnumeration>
          <org.cidrz.webapp.dynasite.valueobject.FieldEnumeration>
            <id>1117</id>
            <fieldId>202</fieldId>
            <enumeration>Penicillin Injection: Dose 1 (2.4 megaunits) week 1</enumeration>
            <numericValue></numericValue>
            <enabled>true</enabled>
            <concatEnumNumeric>Penicillin Injection: Dose 1 (2.4 megaunits) week 1 ()</concatEnumNumeric>
            <displayOrder>2</displayOrder>
          </org.cidrz.webapp.dynasite.valueobject.FieldEnumeration>
          <org.cidrz.webapp.dynasite.valueobject.FieldEnumeration>
            <id>1437</id>
            <fieldId>202</fieldId>
            <enumeration>Penicillin Injection: Dose 2 (2.4 megaunits) week 2</enumeration>
            <numericValue></numericValue>
            <enabled>true</enabled>
            <concatEnumNumeric>Penicillin Injection: Dose 2 (2.4 megaunits) week 2 ()</concatEnumNumeric>
            <displayOrder>3</displayOrder>
          </org.cidrz.webapp.dynasite.valueobject.FieldEnumeration>
          <org.cidrz.webapp.dynasite.valueobject.FieldEnumeration>
            <id>1665</id>
            <fieldId>202</fieldId>
            <enumeration>Penicillin Injection: Dose 3 (2.4 megaunits) week 3</enumeration>
            <numericValue></numericValue>
            <enabled>true</enabled>
            <concatEnumNumeric>Penicillin Injection: Dose 3 (2.4 megaunits) week 3 ()</concatEnumNumeric>
            <displayOrder>4</displayOrder>
          </org.cidrz.webapp.dynasite.valueobject.FieldEnumeration>
          <org.cidrz.webapp.dynasite.valueobject.FieldEnumeration>
            <id>1842</id>
            <fieldId>202</fieldId>
            <enumeration>Other, Describe</enumeration>
            <enabled>true</enabled>
            <displayOrder>5</displayOrder>
          </org.cidrz.webapp.dynasite.valueobject.FieldEnumeration>
        </enumerations>
        <shared>false</shared>
        <starSchemaName>if_reactive_treatment_202</starSchemaName>
        <encounterRecordproperty></encounterRecordproperty>
      </form__field>
      <formFieldId>202</formFieldId>
      <displayOrder>10</displayOrder>
      <inputType>select</inputType>
      <closeRow>true</closeRow>
      <columnNumber>0</columnNumber>
      <size>0</size>
      <maxlength>0</maxlength>
      <rows>0</rows>
      <cols>0</cols>
      <visible>true</visible>
      <visibleEnumIdTrigger1>1842</visibleEnumIdTrigger1>
      <visibleDependencies1>203</visibleDependencies1>
      <formId>9</formId>
      <colspan>2</colspan>
      <dempMap1>
        <entry>
          <string>203</string>
          <long>1429</long>
        </entry>
      </dempMap1>
      <highlightCell>false</highlightCell>
    </org.cidrz.webapp.dynasite.valueobject.PageItem>
    <org.cidrz.webapp.dynasite.valueobject.PageItem>
      <id>1430</id>
      <form__field>
        <id>203</id>
        <label>Treatment, Other, Describe</label>
        <type>Text</type>
        <required>false</required>
        <minValue>0</minValue>
        <maxValue>0</maxValue>
        <units></units>
        <displayOrder>2147483647</displayOrder>
        <patientProperty></patientProperty>
        <isEnabled>true</isEnabled>
        <ruleDefinitions/>
        <enumerations/>
        <shared>false</shared>
        <starSchemaName>treatment_other_203</starSchemaName>
        <encounterRecordproperty></encounterRecordproperty>
      </form__field>
      <formFieldId>203</formFieldId>
      <displayOrder>11</displayOrder>
      <inputType>textarea</inputType>
      <closeRow>true</closeRow>
      <columnNumber>0</columnNumber>
      <size>0</size>
      <maxlength>0</maxlength>
      <rows>0</rows>
      <cols>0</cols>
      <visible>false</visible>
      <visibleEnumIdTrigger1></visibleEnumIdTrigger1>
      <visibleDependencies1></visibleDependencies1>
      <formId>9</formId>
      <colspan>2</colspan>
      <highlightCell>false</highlightCell>
    </org.cidrz.webapp.dynasite.valueobject.PageItem>
    <org.cidrz.webapp.dynasite.valueobject.PageItem>
      <id>1431</id>
      <form__field>
        <id>235</id>
        <label>Hb</label>
        <type>Integer</type>
        <required>false</required>
        <minValue>1</minValue>
        <maxValue>20</maxValue>
        <units>g/dl</units>
        <displayOrder>2147483647</displayOrder>
        <patientProperty></patientProperty>
        <isEnabled>true</isEnabled>
        <ruleDefinitions>
          <org.cidrz.webapp.dynasite.valueobject.RuleDefinition>
            <id>29</id>
            <ruleClass>org.cidrz.webapp.dynasite.rules.impl.SimpleComparison</ruleClass>
            <outcomeClass>org.cidrz.webapp.dynasite.rules.impl.InfoOutcome</outcomeClass>
            <fieldId>235</fieldId>
            <enabled>true</enabled>
            <ruleParams/>
            <outcomeParams/>
            <message>Hb Lab Results: Hb below 10</message>
            <operand>10</operand>
            <operator>lt</operator>
            <allPregnancies>false</allPregnancies>
          </org.cidrz.webapp.dynasite.valueobject.RuleDefinition>
        </ruleDefinitions>
        <enumerations/>
        <shared>true</shared>
        <starSchemaName>hb_235</starSchemaName>
        <encounterRecordproperty></encounterRecordproperty>
        <patientStatusproperty></patientStatusproperty>
      </form__field>
      <formFieldId>235</formFieldId>
      <displayOrder>12</displayOrder>
      <inputType>text</inputType>
      <closeRow>true</closeRow>
      <columnNumber>0</columnNumber>
      <size>2</size>
      <maxlength>2</maxlength>
      <rows>0</rows>
      <cols>0</cols>
      <visible>true</visible>
      <visibleEnumIdTrigger1></visibleEnumIdTrigger1>
      <visibleDependencies1></visibleDependencies1>
      <visibleEnumIdTrigger2></visibleEnumIdTrigger2>
      <selectedEnum>0</selectedEnum>
      <visibleDependencies2></visibleDependencies2>
      <formId>9</formId>
      <colspan>2</colspan>
      <highlightCell>false</highlightCell>
    </org.cidrz.webapp.dynasite.valueobject.PageItem>
    <org.cidrz.webapp.dynasite.valueobject.PageItem>
      <id>1432</id>
      <form__field>
        <id>205</id>
        <label>If Hb not done, Reason</label>
        <type>Enum</type>
        <required>false</required>
        <minValue>0</minValue>
        <maxValue>0</maxValue>
        <units></units>
        <displayOrder>12</displayOrder>
        <patientProperty></patientProperty>
        <isEnabled>true</isEnabled>
        <ruleDefinitions/>
        <enumerations class="tree-set">
          <comparator class="org.cidrz.webapp.dynasite.utils.sort.DisplayOrderComparator"/>
          <org.cidrz.webapp.dynasite.valueobject.FieldEnumeration>
            <id>110</id>
            <fieldId>205</fieldId>
            <enumeration>No Reagents</enumeration>
            <enabled>true</enabled>
            <displayOrder>0</displayOrder>
          </org.cidrz.webapp.dynasite.valueobject.FieldEnumeration>
          <org.cidrz.webapp.dynasite.valueobject.FieldEnumeration>
            <id>642</id>
            <fieldId>205</fieldId>
            <enumeration>Other, Describe</enumeration>
            <enabled>true</enabled>
            <displayOrder>1</displayOrder>
          </org.cidrz.webapp.dynasite.valueobject.FieldEnumeration>
        </enumerations>
        <shared>false</shared>
        <starSchemaName>no_hb_reason_205</starSchemaName>
        <encounterRecordproperty></encounterRecordproperty>
        <patientStatusproperty></patientStatusproperty>
        <patientLabproperty></patientLabproperty>
      </form__field>
      <formFieldId>205</formFieldId>
      <displayOrder>13</displayOrder>
      <inputType>select</inputType>
      <closeRow>false</closeRow>
      <size>0</size>
      <maxlength>0</maxlength>
      <rows>0</rows>
      <cols>0</cols>
      <visible>true</visible>
      <visibleEnumIdTrigger1>642</visibleEnumIdTrigger1>
      <visibleDependencies1>206</visibleDependencies1>
      <formId>9</formId>
      <dempMap1>
        <entry>
          <string>206</string>
          <long>1432</long>
        </entry>
      </dempMap1>
      <highlightCell>false</highlightCell>
    </org.cidrz.webapp.dynasite.valueobject.PageItem>
    <org.cidrz.webapp.dynasite.valueobject.PageItem>
      <id>1433</id>
      <form__field>
        <id>206</id>
        <label>If Hb not done, Reason, Describe</label>
        <type>Text</type>
        <required>false</required>
        <minValue>0</minValue>
        <maxValue>0</maxValue>
        <units></units>
        <displayOrder>13</displayOrder>
        <patientProperty></patientProperty>
        <isEnabled>true</isEnabled>
        <ruleDefinitions/>
        <enumerations/>
        <shared>false</shared>
        <starSchemaName>no_hb_reason_desc_206</starSchemaName>
        <encounterRecordproperty></encounterRecordproperty>
        <patientStatusproperty></patientStatusproperty>
        <patientLabproperty></patientLabproperty>
      </form__field>
      <formFieldId>206</formFieldId>
      <displayOrder>14</displayOrder>
      <inputType>textarea</inputType>
      <closeRow>false</closeRow>
      <size>0</size>
      <maxlength>0</maxlength>
      <rows>0</rows>
      <cols>0</cols>
      <visible>false</visible>
      <visibleDependencies1></visibleDependencies1>
      <formId>9</formId>
      <highlightCell>false</highlightCell>
    </org.cidrz.webapp.dynasite.valueobject.PageItem>
    <org.cidrz.webapp.dynasite.valueobject.PageItem>
      <id>1434</id>
      <form__field>
        <id>207</id>
        <label>Cervical Smear</label>
        <type>Enum</type>
        <required>false</required>
        <minValue>0</minValue>
        <maxValue>0</maxValue>
        <units></units>
        <displayOrder>2147483647</displayOrder>
        <patientProperty></patientProperty>
        <isEnabled>true</isEnabled>
        <ruleDefinitions>
          <org.cidrz.webapp.dynasite.valueobject.RuleDefinition>
            <id>30</id>
            <ruleClass>org.cidrz.webapp.dynasite.rules.impl.SimpleComparison</ruleClass>
            <outcomeClass>org.cidrz.webapp.dynasite.rules.impl.InfoOutcome</outcomeClass>
            <fieldId>207</fieldId>
            <enabled>true</enabled>
            <ruleParams/>
            <outcomeParams/>
            <message>Cervical Smear Lab Test: Positive</message>
            <operand>2</operand>
            <operator>eq</operator>
            <allPregnancies>false</allPregnancies>
          </org.cidrz.webapp.dynasite.valueobject.RuleDefinition>
        </ruleDefinitions>
        <enumerations class="tree-set">
          <comparator class="org.cidrz.webapp.dynasite.utils.sort.DisplayOrderComparator"/>
          <org.cidrz.webapp.dynasite.valueobject.FieldEnumeration>
            <id>643</id>
            <fieldId>207</fieldId>
            <enumeration>Negative</enumeration>
            <numericValue>7</numericValue>
            <enabled>true</enabled>
            <concatEnumNumeric>Negative (7)</concatEnumNumeric>
            <displayOrder>0</displayOrder>
          </org.cidrz.webapp.dynasite.valueobject.FieldEnumeration>
          <org.cidrz.webapp.dynasite.valueobject.FieldEnumeration>
            <id>1118</id>
            <fieldId>207</fieldId>
            <enumeration>Positive</enumeration>
            <numericValue>8</numericValue>
            <enabled>true</enabled>
            <concatEnumNumeric>Positive (8)</concatEnumNumeric>
            <displayOrder>1</displayOrder>
          </org.cidrz.webapp.dynasite.valueobject.FieldEnumeration>
          <org.cidrz.webapp.dynasite.valueobject.FieldEnumeration>
            <id>111</id>
            <fieldId>207</fieldId>
            <enumeration>Not Done</enumeration>
            <numericValue>4</numericValue>
            <enabled>true</enabled>
            <concatEnumNumeric>Not Done (4)</concatEnumNumeric>
            <displayOrder>2</displayOrder>
          </org.cidrz.webapp.dynasite.valueobject.FieldEnumeration>
        </enumerations>
        <shared>true</shared>
        <starSchemaName>cervical_smell_207</starSchemaName>
        <encounterRecordproperty></encounterRecordproperty>
        <patientStatusproperty></patientStatusproperty>
      </form__field>
      <formFieldId>207</formFieldId>
      <displayOrder>15</displayOrder>
      <inputType>select</inputType>
      <closeRow>true</closeRow>
      <columnNumber>0</columnNumber>
      <size>0</size>
      <maxlength>0</maxlength>
      <rows>0</rows>
      <cols>0</cols>
      <visible>true</visible>
      <visibleEnumIdTrigger1>111</visibleEnumIdTrigger1>
      <visibleDependencies1>208</visibleDependencies1>
      <visibleEnumIdTrigger2>-1</visibleEnumIdTrigger2>
      <selectedEnum>-1</selectedEnum>
      <visibleDependencies2></visibleDependencies2>
      <formId>9</formId>
      <colspan>2</colspan>
      <dempMap1>
        <entry>
          <string>208</string>
          <long>1434</long>
        </entry>
      </dempMap1>
      <highlightCell>false</highlightCell>
    </org.cidrz.webapp.dynasite.valueobject.PageItem>
    <org.cidrz.webapp.dynasite.valueobject.PageItem>
      <id>1435</id>
      <form__field>
        <id>208</id>
        <label>If Cervical Smear not done, Reason</label>
        <type>Enum</type>
        <required>false</required>
        <minValue>0</minValue>
        <maxValue>0</maxValue>
        <units></units>
        <displayOrder>15</displayOrder>
        <patientProperty></patientProperty>
        <isEnabled>true</isEnabled>
        <ruleDefinitions/>
        <enumerations class="tree-set">
          <comparator class="org.cidrz.webapp.dynasite.utils.sort.DisplayOrderComparator"/>
          <org.cidrz.webapp.dynasite.valueobject.FieldEnumeration>
            <id>112</id>
            <fieldId>208</fieldId>
            <enumeration>No Reagents</enumeration>
            <enabled>true</enabled>
            <displayOrder>0</displayOrder>
          </org.cidrz.webapp.dynasite.valueobject.FieldEnumeration>
          <org.cidrz.webapp.dynasite.valueobject.FieldEnumeration>
            <id>644</id>
            <fieldId>208</fieldId>
            <enumeration>No Equipment</enumeration>
            <enabled>true</enabled>
            <displayOrder>1</displayOrder>
          </org.cidrz.webapp.dynasite.valueobject.FieldEnumeration>
          <org.cidrz.webapp.dynasite.valueobject.FieldEnumeration>
            <id>1119</id>
            <fieldId>208</fieldId>
            <enumeration>Other, Describe</enumeration>
            <enabled>true</enabled>
            <displayOrder>2</displayOrder>
          </org.cidrz.webapp.dynasite.valueobject.FieldEnumeration>
        </enumerations>
        <shared>false</shared>
        <starSchemaName>no_cervical_reason_208</starSchemaName>
        <encounterRecordproperty></encounterRecordproperty>
        <patientStatusproperty></patientStatusproperty>
        <patientLabproperty></patientLabproperty>
      </form__field>
      <formFieldId>208</formFieldId>
      <displayOrder>16</displayOrder>
      <inputType>select</inputType>
      <closeRow>false</closeRow>
      <size>0</size>
      <maxlength>0</maxlength>
      <rows>0</rows>
      <cols>0</cols>
      <visible>false</visible>
      <visibleEnumIdTrigger1>1119</visibleEnumIdTrigger1>
      <visibleDependencies1>209</visibleDependencies1>
      <formId>9</formId>
      <dempMap1>
        <entry>
          <string>209</string>
          <long>1435</long>
        </entry>
      </dempMap1>
      <highlightCell>false</highlightCell>
    </org.cidrz.webapp.dynasite.valueobject.PageItem>
    <org.cidrz.webapp.dynasite.valueobject.PageItem>
      <id>1442</id>
      <form__field>
        <id>209</id>
        <label>If Cervical Smear not done, Reason, Describe</label>
        <type>Text</type>
        <required>false</required>
        <minValue>0</minValue>
        <maxValue>0</maxValue>
        <units></units>
        <displayOrder>16</displayOrder>
        <patientProperty></patientProperty>
        <isEnabled>true</isEnabled>
        <ruleDefinitions/>
        <enumerations/>
        <shared>false</shared>
        <starSchemaName>no_cervical_reason_desc_209</starSchemaName>
        <encounterRecordproperty></encounterRecordproperty>
        <patientStatusproperty></patientStatusproperty>
        <patientLabproperty></patientLabproperty>
      </form__field>
      <formFieldId>209</formFieldId>
      <displayOrder>17</displayOrder>
      <inputType>textarea</inputType>
      <closeRow>false</closeRow>
      <size>0</size>
      <maxlength>0</maxlength>
      <rows>0</rows>
      <cols>0</cols>
      <visible>false</visible>
      <visibleDependencies1></visibleDependencies1>
      <formId>9</formId>
      <highlightCell>false</highlightCell>
    </org.cidrz.webapp.dynasite.valueobject.PageItem>
    <org.cidrz.webapp.dynasite.valueobject.PageItem>
      <id>1437</id>
      <form__field>
        <id>210</id>
        <label>Accepts HIV Test Today</label>
        <type>Yes/No</type>
        <required>false</required>
        <minValue>0</minValue>
        <maxValue>0</maxValue>
        <units></units>
        <displayOrder>17</displayOrder>
        <patientProperty></patientProperty>
        <isEnabled>true</isEnabled>
        <ruleDefinitions/>
        <enumerations/>
        <shared>false</shared>
        <starSchemaName>accepts_hiv_today_210</starSchemaName>
        <encounterRecordproperty></encounterRecordproperty>
        <patientStatusproperty></patientStatusproperty>
        <patientLabproperty></patientLabproperty>
      </form__field>
      <formFieldId>210</formFieldId>
      <displayOrder>18</displayOrder>
      <inputType>select</inputType>
      <closeRow>false</closeRow>
      <size>0</size>
      <maxlength>0</maxlength>
      <rows>0</rows>
      <cols>0</cols>
      <visible>true</visible>
      <visibleEnumIdTrigger1>0</visibleEnumIdTrigger1>
      <visibleDependencies1></visibleDependencies1>
      <formId>9</formId>
      <highlightCell>false</highlightCell>
    </org.cidrz.webapp.dynasite.valueobject.PageItem>
    <org.cidrz.webapp.dynasite.valueobject.PageItem>
      <id>211</id>
      <form__field>
        <id>211</id>
        <label>HIV Result</label>
        <type>Enum</type>
        <required>false</required>
        <minValue>0</minValue>
        <maxValue>0</maxValue>
        <units></units>
        <displayOrder>2147483647</displayOrder>
        <patientProperty></patientProperty>
        <isEnabled>true</isEnabled>
        <ruleDefinitions>
          <org.cidrz.webapp.dynasite.valueobject.RuleDefinition>
            <id>31</id>
            <ruleClass>org.cidrz.webapp.dynasite.rules.impl.SimpleComparison</ruleClass>
            <outcomeClass>org.cidrz.webapp.dynasite.rules.impl.InfoOutcome</outcomeClass>
            <fieldId>211</fieldId>
            <enabled>true</enabled>
            <ruleParams/>
            <outcomeParams/>
            <message>HIV Result</message>
            <operand>1</operand>
            <operator>eq</operator>
            <allPregnancies>false</allPregnancies>
          </org.cidrz.webapp.dynasite.valueobject.RuleDefinition>
        </ruleDefinitions>
        <enumerations class="tree-set">
          <comparator class="org.cidrz.webapp.dynasite.utils.sort.DisplayOrderComparator"/>
          <org.cidrz.webapp.dynasite.valueobject.FieldEnumeration>
            <id>114</id>
            <fieldId>211</fieldId>
            <enumeration>Non-Reactive (Negative)</enumeration>
            <numericValue>0</numericValue>
            <enabled>true</enabled>
            <concatEnumNumeric>Non-Reactive (Negative) (0)</concatEnumNumeric>
            <displayOrder>0</displayOrder>
          </org.cidrz.webapp.dynasite.valueobject.FieldEnumeration>
          <org.cidrz.webapp.dynasite.valueobject.FieldEnumeration>
            <id>646</id>
            <fieldId>211</fieldId>
            <enumeration>Reactive (Positive)</enumeration>
            <numericValue>1</numericValue>
            <enabled>true</enabled>
            <concatEnumNumeric>Reactive (Positive) (1)</concatEnumNumeric>
            <displayOrder>0</displayOrder>
          </org.cidrz.webapp.dynasite.valueobject.FieldEnumeration>
          <org.cidrz.webapp.dynasite.valueobject.FieldEnumeration>
            <id>2579</id>
            <fieldId>211</fieldId>
            <enumeration>Indeterminate</enumeration>
            <numericValue>2</numericValue>
            <enabled>true</enabled>
            <concatEnumNumeric>Indeterminate (2)</concatEnumNumeric>
            <displayOrder>2147483647</displayOrder>
          </org.cidrz.webapp.dynasite.valueobject.FieldEnumeration>
        </enumerations>
        <shared>false</shared>
        <starSchemaName>hiv_result_211</starSchemaName>
        <encounterRecordproperty></encounterRecordproperty>
        <patientStatusproperty></patientStatusproperty>
        <patientLabproperty></patientLabproperty>
      </form__field>
      <formFieldId>211</formFieldId>
      <displayOrder>19</displayOrder>
      <inputType>select</inputType>
      <closeRow>false</closeRow>
      <columnNumber>0</columnNumber>
      <size>0</size>
      <maxlength>0</maxlength>
      <rows>0</rows>
      <cols>0</cols>
      <visible>true</visible>
      <visibleEnumIdTrigger1>-1</visibleEnumIdTrigger1>
      <visibleDependencies1></visibleDependencies1>
      <formId>9</formId>
      <colspan>0</colspan>
      <highlightCell>false</highlightCell>
    </org.cidrz.webapp.dynasite.valueobject.PageItem>
    <org.cidrz.webapp.dynasite.valueobject.PageItem>
      <id>2813</id>
      <form__field>
        <id>1459</id>
        <label>Sickle Cell Test</label>
        <type>Yes/No</type>
        <required>false</required>
        <minValue>0</minValue>
        <maxValue>0</maxValue>
        <units></units>
        <displayOrder>2147483647</displayOrder>
        <patientProperty></patientProperty>
        <isEnabled>true</isEnabled>
        <ruleDefinitions/>
        <enumerations/>
        <shared>false</shared>
        <starSchemaName>sickle_cell_test</starSchemaName>
        <encounterRecordproperty></encounterRecordproperty>
        <patientStatusproperty></patientStatusproperty>
      </form__field>
      <formFieldId>1459</formFieldId>
      <displayOrder>20</displayOrder>
      <inputType>text</inputType>
      <closeRow>false</closeRow>
      <columnNumber>0</columnNumber>
      <size>0</size>
      <maxlength>0</maxlength>
      <rows>0</rows>
      <cols>0</cols>
      <visible>true</visible>
      <visibleEnumIdTrigger1>1</visibleEnumIdTrigger1>
      <visibleDependencies1>1460</visibleDependencies1>
      <formId>9</formId>
      <colspan>0</colspan>
      <dempMap1>
        <entry>
          <string>1460</string>
          <long>2813</long>
        </entry>
      </dempMap1>
      <highlightCell>false</highlightCell>
    </org.cidrz.webapp.dynasite.valueobject.PageItem>
    <org.cidrz.webapp.dynasite.valueobject.PageItem>
      <id>2814</id>
      <form__field>
        <id>1460</id>
        <label>Sickle Cell Screen</label>
        <type>Enum</type>
        <required>false</required>
        <minValue>0</minValue>
        <maxValue>0</maxValue>
        <units></units>
        <displayOrder>2147483647</displayOrder>
        <patientProperty></patientProperty>
        <isEnabled>true</isEnabled>
        <ruleDefinitions>
          <org.cidrz.webapp.dynasite.valueobject.RuleDefinition>
            <id>32</id>
            <ruleClass>org.cidrz.webapp.dynasite.rules.impl.SimpleComparison</ruleClass>
            <outcomeClass>org.cidrz.webapp.dynasite.rules.impl.InfoOutcome</outcomeClass>
            <fieldId>1460</fieldId>
            <enabled>true</enabled>
            <ruleParams/>
            <outcomeParams/>
            <message>Sickle Cell Test Results: Patient has condition.</message>
            <operand>0</operand>
            <operator>ne</operator>
            <allPregnancies>false</allPregnancies>
          </org.cidrz.webapp.dynasite.valueobject.RuleDefinition>
        </ruleDefinitions>
        <enumerations class="tree-set">
          <comparator class="org.cidrz.webapp.dynasite.utils.sort.DisplayOrderComparator"/>
          <org.cidrz.webapp.dynasite.valueobject.FieldEnumeration>
            <id>2737</id>
            <fieldId>1460</fieldId>
            <enumeration>Normal</enumeration>
            <numericValue>9</numericValue>
            <enabled>true</enabled>
            <concatEnumNumeric>Normal (9)</concatEnumNumeric>
            <displayOrder>0</displayOrder>
          </org.cidrz.webapp.dynasite.valueobject.FieldEnumeration>
          <org.cidrz.webapp.dynasite.valueobject.FieldEnumeration>
            <id>2735</id>
            <fieldId>1460</fieldId>
            <enumeration>Sickle Cell Anaemia</enumeration>
            <numericValue>10</numericValue>
            <enabled>true</enabled>
            <concatEnumNumeric>Sickle Cell Anaemia (10)</concatEnumNumeric>
            <displayOrder>1</displayOrder>
          </org.cidrz.webapp.dynasite.valueobject.FieldEnumeration>
          <org.cidrz.webapp.dynasite.valueobject.FieldEnumeration>
            <id>2736</id>
            <fieldId>1460</fieldId>
            <enumeration>Sickle Cell Trait</enumeration>
            <numericValue>11</numericValue>
            <enabled>true</enabled>
            <concatEnumNumeric>Sickle Cell Trait (11)</concatEnumNumeric>
            <displayOrder>2</displayOrder>
          </org.cidrz.webapp.dynasite.valueobject.FieldEnumeration>
        </enumerations>
        <shared>true</shared>
        <starSchemaName>sickle_cell_screen</starSchemaName>
        <encounterRecordproperty></encounterRecordproperty>
        <patientStatusproperty></patientStatusproperty>
      </form__field>
      <formFieldId>1460</formFieldId>
      <displayOrder>21</displayOrder>
      <inputType>select</inputType>
      <closeRow>false</closeRow>
      <columnNumber>0</columnNumber>
      <size>0</size>
      <maxlength>0</maxlength>
      <rows>0</rows>
      <cols>0</cols>
      <visible>false</visible>
      <visibleEnumIdTrigger1>-1</visibleEnumIdTrigger1>
      <visibleDependencies1></visibleDependencies1>
      <visibleEnumIdTrigger2>-1</visibleEnumIdTrigger2>
      <selectedEnum>-1</selectedEnum>
      <visibleDependencies2></visibleDependencies2>
      <formId>9</formId>
      <colspan>0</colspan>
      <highlightCell>false</highlightCell>
    </org.cidrz.webapp.dynasite.valueobject.PageItem>
    <org.cidrz.webapp.dynasite.valueobject.PageItem>
      <id>2815</id>
      <form__field>
        <id>1461</id>
        <label>Malaria Test</label>
        <type>Yes/No</type>
        <required>false</required>
        <minValue>0</minValue>
        <maxValue>0</maxValue>
        <units></units>
        <displayOrder>2147483647</displayOrder>
        <patientProperty></patientProperty>
        <isEnabled>true</isEnabled>
        <ruleDefinitions/>
        <enumerations/>
        <shared>false</shared>
        <starSchemaName>malaria_test</starSchemaName>
        <encounterRecordproperty></encounterRecordproperty>
        <patientStatusproperty></patientStatusproperty>
      </form__field>
      <formFieldId>1461</formFieldId>
      <displayOrder>22</displayOrder>
      <inputType>text</inputType>
      <closeRow>false</closeRow>
      <columnNumber>0</columnNumber>
      <size>0</size>
      <maxlength>0</maxlength>
      <rows>0</rows>
      <cols>0</cols>
      <visible>true</visible>
      <visibleEnumIdTrigger1>1</visibleEnumIdTrigger1>
      <visibleDependencies1>1462</visibleDependencies1>
      <formId>9</formId>
      <colspan>0</colspan>
      <dempMap1>
        <entry>
          <string>1462</string>
          <long>2815</long>
        </entry>
      </dempMap1>
      <highlightCell>false</highlightCell>
    </org.cidrz.webapp.dynasite.valueobject.PageItem>
    <org.cidrz.webapp.dynasite.valueobject.PageItem>
      <id>2816</id>
      <form__field>
        <id>1462</id>
        <label>Malaria Test Results</label>
        <type>Enum</type>
        <required>false</required>
        <minValue>0</minValue>
        <maxValue>0</maxValue>
        <units></units>
        <displayOrder>2147483647</displayOrder>
        <patientProperty></patientProperty>
        <isEnabled>true</isEnabled>
        <ruleDefinitions>
          <org.cidrz.webapp.dynasite.valueobject.RuleDefinition>
            <id>33</id>
            <ruleClass>org.cidrz.webapp.dynasite.rules.impl.SimpleComparison</ruleClass>
            <outcomeClass>org.cidrz.webapp.dynasite.rules.impl.InfoOutcome</outcomeClass>
            <fieldId>1462</fieldId>
            <enabled>true</enabled>
            <ruleParams/>
            <outcomeParams/>
            <message>Malaria Test Results: positive</message>
            <operand>1</operand>
            <operator>eq</operator>
            <allPregnancies>false</allPregnancies>
          </org.cidrz.webapp.dynasite.valueobject.RuleDefinition>
        </ruleDefinitions>
        <enumerations class="tree-set">
          <comparator class="org.cidrz.webapp.dynasite.utils.sort.DisplayOrderComparator"/>
          <org.cidrz.webapp.dynasite.valueobject.FieldEnumeration>
            <id>2739</id>
            <fieldId>1462</fieldId>
            <enumeration>Negative</enumeration>
            <numericValue>12</numericValue>
            <enabled>true</enabled>
            <concatEnumNumeric>Negative (12)</concatEnumNumeric>
            <displayOrder>2147483647</displayOrder>
          </org.cidrz.webapp.dynasite.valueobject.FieldEnumeration>
          <org.cidrz.webapp.dynasite.valueobject.FieldEnumeration>
            <id>2740</id>
            <fieldId>1462</fieldId>
            <enumeration>Positive</enumeration>
            <numericValue>13</numericValue>
            <enabled>true</enabled>
            <concatEnumNumeric>Positive (13)</concatEnumNumeric>
            <displayOrder>2147483647</displayOrder>
          </org.cidrz.webapp.dynasite.valueobject.FieldEnumeration>
        </enumerations>
        <shared>true</shared>
        <starSchemaName>malaria_test_results</starSchemaName>
        <encounterRecordproperty></encounterRecordproperty>
        <patientStatusproperty></patientStatusproperty>
      </form__field>
      <formFieldId>1462</formFieldId>
      <displayOrder>23</displayOrder>
      <inputType>text</inputType>
      <closeRow>false</closeRow>
      <columnNumber>0</columnNumber>
      <size>0</size>
      <maxlength>0</maxlength>
      <rows>0</rows>
      <cols>0</cols>
      <visible>false</visible>
      <visibleEnumIdTrigger1>-1</visibleEnumIdTrigger1>
      <visibleDependencies1></visibleDependencies1>
      <visibleEnumIdTrigger2>-1</visibleEnumIdTrigger2>
      <selectedEnum>-1</selectedEnum>
      <visibleDependencies2></visibleDependencies2>
      <formId>9</formId>
      <colspan>0</colspan>
      <highlightCell>false</highlightCell>
    </org.cidrz.webapp.dynasite.valueobject.PageItem>
    <org.cidrz.webapp.dynasite.valueobject.PageItem>
      <id>2801</id>
      <form__field>
        <id>1428</id>
        <label>END TABLE</label>
        <type>Display</type>
        <required>false</required>
        <minValue>0</minValue>
        <maxValue>0</maxValue>
        <units></units>
        <displayOrder>2147483647</displayOrder>
        <patientProperty></patientProperty>
        <isEnabled>true</isEnabled>
        <ruleDefinitions/>
        <enumerations/>
        <shared>true</shared>
        <starSchemaName></starSchemaName>
        <encounterRecordproperty></encounterRecordproperty>
      </form__field>
      <formFieldId>1428</formFieldId>
      <displayOrder>27</displayOrder>
      <inputType>display-tbl-end</inputType>
      <closeRow>false</closeRow>
      <columnNumber>0</columnNumber>
      <size>0</size>
      <maxlength>0</maxlength>
      <rows>0</rows>
      <cols>1</cols>
      <visible>true</visible>
      <formId>9</formId>
      <colspan>0</colspan>
      <highlightCell>false</highlightCell>
    </org.cidrz.webapp.dynasite.valueobject.PageItem>
  </pageItems>
  <formfields class="tree-set">
    <comparator class="org.cidrz.webapp.dynasite.utils.sort.DisplayOrderComparator"/>
  </formfields>
  <submissions>0</submissions>
  <maxSubmissions>100</maxSubmissions>
</org.cidrz.webapp.dynasite.valueobject.Form>