<?xml version="1.0"?>
<!--
  ~    Copyright 2003, 2004, 2005, 2006 Research Triangle Institute
  ~
  ~    Licensed under the Apache License, Version 2.0 (the "License");
  ~    you may not use this file except in compliance with the License.
  ~    You may obtain a copy of the License at
  ~
  ~        http://www.apache.org/licenses/LICENSE-2.0
  -->

<org.cidrz.webapp.dynasite.valueobject.Form>
  <id>37</id>
  <name>nicuSummaryAdm</name>
  <label>Summary of Admission of Infant at NICU</label>
  <requireReauth>true</requireReauth>
  <requirePatient>true</requirePatient>
  <enabled>true</enabled>
  <ruleDefinitions/>
  <flow>
    <id>5</id>
    <name>NICU</name>
    <flowOrder>5</flowOrder>
    <forms class="tree-set">
      <comparator class="org.cidrz.webapp.dynasite.utils.sort.FlowOrderComparator"/>
    </forms>
  </flow>
  <flowId>5</flowId>
  <flowOrder>2</flowOrder>
  <formType>
    <id>2</id>
    <name>Newborn Only</name>
  </formType>
  <formTypeId>2</formTypeId>
  <pageItems class="tree-set">
    <comparator class="org.cidrz.webapp.dynasite.utils.sort.DisplayOrderComparator"/>
    <org.cidrz.webapp.dynasite.valueobject.PageItem>
      <id>2780</id>
      <form__field>
        <id>1427</id>
        <label>BEGIN TABLE</label>
        <type>Display</type>
        <required>false</required>
        <minValue>0</minValue>
        <maxValue>0</maxValue>
        <units></units>
        <displayOrder>2147483647</displayOrder>
        <patientProperty></patientProperty>
        <isEnabled>true</isEnabled>
        <ruleDefinitions/>
        <enumerations/>
        <shared>true</shared>
        <starSchemaName></starSchemaName>
        <encounterRecordproperty></encounterRecordproperty>
        <patientStatusproperty></patientStatusproperty>
      </form__field>
      <formFieldId>1427</formFieldId>
      <displayOrder>0</displayOrder>
      <inputType>display-tbl-begin</inputType>
      <closeRow>false</closeRow>
      <columnNumber>0</columnNumber>
      <size>0</size>
      <maxlength>0</maxlength>
      <rows>0</rows>
      <cols>2</cols>
      <visible>true</visible>
      <formId>37</formId>
      <colspan>0</colspan>
    </org.cidrz.webapp.dynasite.valueobject.PageItem>
    <org.cidrz.webapp.dynasite.valueobject.PageItem>
      <id>1858</id>
      <form__field>
        <id>816</id>
        <label>Investigations</label>
        <type>Text</type>
        <required>false</required>
        <minValue>0</minValue>
        <maxValue>0</maxValue>
        <units></units>
        <displayOrder>2147483647</displayOrder>
        <patientProperty></patientProperty>
        <isEnabled>true</isEnabled>
        <ruleDefinitions/>
        <enumerations/>
        <shared>false</shared>
        <starSchemaName>investigations</starSchemaName>
        <encounterRecordproperty></encounterRecordproperty>
      </form__field>
      <formFieldId>816</formFieldId>
      <displayOrder>1</displayOrder>
      <inputType>textarea</inputType>
      <closeRow>true</closeRow>
      <columnNumber>0</columnNumber>
      <size>0</size>
      <maxlength>0</maxlength>
      <rows>5</rows>
      <cols>40</cols>
      <visible>true</visible>
      <visibleEnumIdTrigger1></visibleEnumIdTrigger1>
      <visibleDependencies1></visibleDependencies1>
      <formId>37</formId>
      <colspan>2</colspan>
    </org.cidrz.webapp.dynasite.valueobject.PageItem>
    <org.cidrz.webapp.dynasite.valueobject.PageItem>
      <id>2656</id>
      <form__field>
        <id>1372</id>
        <label>Treatment / Interventions</label>
        <type>Display</type>
        <required>false</required>
        <minValue>0</minValue>
        <maxValue>0</maxValue>
        <units></units>
        <displayOrder>2147483647</displayOrder>
        <patientProperty></patientProperty>
        <isEnabled>true</isEnabled>
        <ruleDefinitions/>
        <enumerations/>
        <shared>false</shared>
        <starSchemaName></starSchemaName>
        <encounterRecordproperty></encounterRecordproperty>
      </form__field>
      <formFieldId>1372</formFieldId>
      <displayOrder>2</displayOrder>
      <inputType>display-header</inputType>
      <closeRow>false</closeRow>
      <columnNumber>0</columnNumber>
      <size>0</size>
      <maxlength>0</maxlength>
      <rows>0</rows>
      <cols>2</cols>
      <visible>true</visible>
      <visibleEnumIdTrigger1></visibleEnumIdTrigger1>
      <visibleDependencies1></visibleDependencies1>
      <formId>37</formId>
      <colspan>0</colspan>
    </org.cidrz.webapp.dynasite.valueobject.PageItem>
    <org.cidrz.webapp.dynasite.valueobject.PageItem>
      <id>2657</id>
      <form__field>
        <id>1373</id>
        <label>Oxygen - not ventilated</label>
        <type>Enum</type>
        <required>false</required>
        <minValue>0</minValue>
        <maxValue>0</maxValue>
        <units></units>
        <displayOrder>2147483647</displayOrder>
        <patientProperty></patientProperty>
        <isEnabled>true</isEnabled>
        <ruleDefinitions/>
        <enumerations/>
        <shared>false</shared>
        <starSchemaName>oxygen_not_ventilated</starSchemaName>
        <encounterRecordproperty></encounterRecordproperty>
      </form__field>
      <formFieldId>1373</formFieldId>
      <displayOrder>3</displayOrder>
      <inputType>checkbox</inputType>
      <closeRow>false</closeRow>
      <columnNumber>0</columnNumber>
      <size>0</size>
      <maxlength>0</maxlength>
      <rows>0</rows>
      <cols>0</cols>
      <visible>true</visible>
      <visibleEnumIdTrigger1></visibleEnumIdTrigger1>
      <visibleDependencies1></visibleDependencies1>
      <formId>37</formId>
      <colspan>0</colspan>
    </org.cidrz.webapp.dynasite.valueobject.PageItem>
    <org.cidrz.webapp.dynasite.valueobject.PageItem>
      <id>2659</id>
      <form__field>
        <id>1375</id>
        <label>Mechanical Ventilation</label>
        <type>Enum</type>
        <required>false</required>
        <minValue>0</minValue>
        <maxValue>0</maxValue>
        <units></units>
        <displayOrder>2147483647</displayOrder>
        <patientProperty></patientProperty>
        <isEnabled>true</isEnabled>
        <ruleDefinitions/>
        <enumerations/>
        <shared>false</shared>
        <starSchemaName>mechanical_ventilation</starSchemaName>
        <encounterRecordproperty></encounterRecordproperty>
      </form__field>
      <formFieldId>1375</formFieldId>
      <displayOrder>4</displayOrder>
      <inputType>checkbox</inputType>
      <closeRow>false</closeRow>
      <columnNumber>0</columnNumber>
      <size>0</size>
      <maxlength>0</maxlength>
      <rows>0</rows>
      <cols>0</cols>
      <visible>true</visible>
      <visibleEnumIdTrigger1></visibleEnumIdTrigger1>
      <visibleDependencies1></visibleDependencies1>
      <formId>37</formId>
      <colspan>0</colspan>
    </org.cidrz.webapp.dynasite.valueobject.PageItem>
    <org.cidrz.webapp.dynasite.valueobject.PageItem>
      <id>2658</id>
      <form__field>
        <id>1374</id>
        <label>Antibiotics (list Antibiotics used below)</label>
        <type>Enum</type>
        <required>false</required>
        <minValue>0</minValue>
        <maxValue>0</maxValue>
        <units></units>
        <displayOrder>2147483647</displayOrder>
        <patientProperty></patientProperty>
        <isEnabled>true</isEnabled>
        <ruleDefinitions/>
        <enumerations/>
        <shared>false</shared>
        <starSchemaName>antibiotics</starSchemaName>
        <encounterRecordproperty></encounterRecordproperty>
      </form__field>
      <formFieldId>1374</formFieldId>
      <displayOrder>5</displayOrder>
      <inputType>checkbox</inputType>
      <closeRow>false</closeRow>
      <columnNumber>0</columnNumber>
      <size>0</size>
      <maxlength>0</maxlength>
      <rows>0</rows>
      <cols>0</cols>
      <visible>true</visible>
      <visibleEnumIdTrigger1>-1</visibleEnumIdTrigger1>
      <visibleDependencies1></visibleDependencies1>
      <formId>37</formId>
      <colspan>0</colspan>
    </org.cidrz.webapp.dynasite.valueobject.PageItem>
    <org.cidrz.webapp.dynasite.valueobject.PageItem>
      <id>2660</id>
      <form__field>
        <id>1376</id>
        <label>Nevirapine</label>
        <type>Enum</type>
        <required>false</required>
        <minValue>0</minValue>
        <maxValue>0</maxValue>
        <units></units>
        <displayOrder>2147483647</displayOrder>
        <patientProperty></patientProperty>
        <isEnabled>true</isEnabled>
        <ruleDefinitions/>
        <enumerations/>
        <shared>false</shared>
        <starSchemaName>nevirapine</starSchemaName>
        <encounterRecordproperty></encounterRecordproperty>
      </form__field>
      <formFieldId>1376</formFieldId>
      <displayOrder>6</displayOrder>
      <inputType>checkbox</inputType>
      <closeRow>false</closeRow>
      <columnNumber>0</columnNumber>
      <size>0</size>
      <maxlength>0</maxlength>
      <rows>0</rows>
      <cols>0</cols>
      <visible>true</visible>
      <visibleEnumIdTrigger1></visibleEnumIdTrigger1>
      <visibleDependencies1></visibleDependencies1>
      <formId>37</formId>
      <colspan>0</colspan>
    </org.cidrz.webapp.dynasite.valueobject.PageItem>
    <org.cidrz.webapp.dynasite.valueobject.PageItem>
      <id>2661</id>
      <form__field>
        <id>1377</id>
        <label>Pressors</label>
        <type>Enum</type>
        <required>false</required>
        <minValue>0</minValue>
        <maxValue>0</maxValue>
        <units></units>
        <displayOrder>2147483647</displayOrder>
        <patientProperty></patientProperty>
        <isEnabled>true</isEnabled>
        <ruleDefinitions/>
        <enumerations/>
        <shared>false</shared>
        <starSchemaName>pressors</starSchemaName>
        <encounterRecordproperty></encounterRecordproperty>
      </form__field>
      <formFieldId>1377</formFieldId>
      <displayOrder>7</displayOrder>
      <inputType>checkbox</inputType>
      <closeRow>false</closeRow>
      <columnNumber>0</columnNumber>
      <size>0</size>
      <maxlength>0</maxlength>
      <rows>0</rows>
      <cols>0</cols>
      <visible>true</visible>
      <visibleEnumIdTrigger1></visibleEnumIdTrigger1>
      <visibleDependencies1></visibleDependencies1>
      <formId>37</formId>
      <colspan>0</colspan>
    </org.cidrz.webapp.dynasite.valueobject.PageItem>
    <org.cidrz.webapp.dynasite.valueobject.PageItem>
      <id>2662</id>
      <form__field>
        <id>1378</id>
        <label>Intravenous Fluids</label>
        <type>Enum</type>
        <required>false</required>
        <minValue>0</minValue>
        <maxValue>0</maxValue>
        <units></units>
        <displayOrder>2147483647</displayOrder>
        <patientProperty></patientProperty>
        <isEnabled>true</isEnabled>
        <ruleDefinitions/>
        <enumerations/>
        <shared>false</shared>
        <starSchemaName>intravenous_fluids</starSchemaName>
        <encounterRecordproperty></encounterRecordproperty>
      </form__field>
      <formFieldId>1378</formFieldId>
      <displayOrder>8</displayOrder>
      <inputType>checkbox</inputType>
      <closeRow>false</closeRow>
      <columnNumber>0</columnNumber>
      <size>0</size>
      <maxlength>0</maxlength>
      <rows>0</rows>
      <cols>0</cols>
      <visible>true</visible>
      <visibleEnumIdTrigger1></visibleEnumIdTrigger1>
      <visibleDependencies1></visibleDependencies1>
      <formId>37</formId>
      <colspan>0</colspan>
    </org.cidrz.webapp.dynasite.valueobject.PageItem>
    <org.cidrz.webapp.dynasite.valueobject.PageItem>
      <id>2663</id>
      <form__field>
        <id>1379</id>
        <label>Umbilical Artery Catheter</label>
        <type>Enum</type>
        <required>false</required>
        <minValue>0</minValue>
        <maxValue>0</maxValue>
        <units></units>
        <displayOrder>2147483647</displayOrder>
        <patientProperty></patientProperty>
        <isEnabled>true</isEnabled>
        <ruleDefinitions/>
        <enumerations/>
        <shared>false</shared>
        <starSchemaName>umbilical_artery_catheter</starSchemaName>
        <encounterRecordproperty></encounterRecordproperty>
      </form__field>
      <formFieldId>1379</formFieldId>
      <displayOrder>9</displayOrder>
      <inputType>checkbox</inputType>
      <closeRow>false</closeRow>
      <columnNumber>0</columnNumber>
      <size>0</size>
      <maxlength>0</maxlength>
      <rows>0</rows>
      <cols>0</cols>
      <visible>true</visible>
      <visibleEnumIdTrigger1></visibleEnumIdTrigger1>
      <visibleDependencies1></visibleDependencies1>
      <formId>37</formId>
      <colspan>0</colspan>
    </org.cidrz.webapp.dynasite.valueobject.PageItem>
    <org.cidrz.webapp.dynasite.valueobject.PageItem>
      <id>2664</id>
      <form__field>
        <id>1380</id>
        <label>XS Transfusion</label>
        <type>Enum</type>
        <required>false</required>
        <minValue>0</minValue>
        <maxValue>0</maxValue>
        <units></units>
        <displayOrder>2147483647</displayOrder>
        <patientProperty></patientProperty>
        <isEnabled>true</isEnabled>
        <ruleDefinitions/>
        <enumerations/>
        <shared>false</shared>
        <starSchemaName>xs_transfusion</starSchemaName>
        <encounterRecordproperty></encounterRecordproperty>
      </form__field>
      <formFieldId>1380</formFieldId>
      <displayOrder>10</displayOrder>
      <inputType>checkbox</inputType>
      <closeRow>false</closeRow>
      <columnNumber>0</columnNumber>
      <size>0</size>
      <maxlength>0</maxlength>
      <rows>0</rows>
      <cols>0</cols>
      <visible>true</visible>
      <visibleEnumIdTrigger1></visibleEnumIdTrigger1>
      <visibleDependencies1></visibleDependencies1>
      <formId>37</formId>
      <colspan>0</colspan>
    </org.cidrz.webapp.dynasite.valueobject.PageItem>
    <org.cidrz.webapp.dynasite.valueobject.PageItem>
      <id>2665</id>
      <form__field>
        <id>1381</id>
        <label>Phototherapy</label>
        <type>Enum</type>
        <required>false</required>
        <minValue>0</minValue>
        <maxValue>0</maxValue>
        <units></units>
        <displayOrder>2147483647</displayOrder>
        <patientProperty></patientProperty>
        <isEnabled>true</isEnabled>
        <ruleDefinitions/>
        <enumerations/>
        <shared>false</shared>
        <starSchemaName>phototherapy</starSchemaName>
        <encounterRecordproperty></encounterRecordproperty>
      </form__field>
      <formFieldId>1381</formFieldId>
      <displayOrder>11</displayOrder>
      <inputType>checkbox</inputType>
      <closeRow>false</closeRow>
      <columnNumber>0</columnNumber>
      <size>0</size>
      <maxlength>0</maxlength>
      <rows>0</rows>
      <cols>0</cols>
      <visible>true</visible>
      <visibleEnumIdTrigger1></visibleEnumIdTrigger1>
      <visibleDependencies1></visibleDependencies1>
      <formId>37</formId>
      <colspan>0</colspan>
    </org.cidrz.webapp.dynasite.valueobject.PageItem>
    <org.cidrz.webapp.dynasite.valueobject.PageItem>
      <id>2666</id>
      <form__field>
        <id>1382</id>
        <label>Vitamin K</label>
        <type>Enum</type>
        <required>false</required>
        <minValue>0</minValue>
        <maxValue>0</maxValue>
        <units></units>
        <displayOrder>2147483647</displayOrder>
        <patientProperty></patientProperty>
        <isEnabled>true</isEnabled>
        <ruleDefinitions/>
        <enumerations/>
        <shared>false</shared>
        <starSchemaName>vitamin_k</starSchemaName>
        <encounterRecordproperty></encounterRecordproperty>
      </form__field>
      <formFieldId>1382</formFieldId>
      <displayOrder>12</displayOrder>
      <inputType>checkbox</inputType>
      <closeRow>false</closeRow>
      <columnNumber>0</columnNumber>
      <size>0</size>
      <maxlength>0</maxlength>
      <rows>0</rows>
      <cols>0</cols>
      <visible>true</visible>
      <visibleEnumIdTrigger1></visibleEnumIdTrigger1>
      <visibleDependencies1></visibleDependencies1>
      <formId>37</formId>
      <colspan>0</colspan>
    </org.cidrz.webapp.dynasite.valueobject.PageItem>
    <org.cidrz.webapp.dynasite.valueobject.PageItem>
      <id>2667</id>
      <form__field>
        <id>1383</id>
        <label>Treatment: Other, Describe</label>
        <type>Enum</type>
        <required>false</required>
        <minValue>0</minValue>
        <maxValue>0</maxValue>
        <units></units>
        <displayOrder>2147483647</displayOrder>
        <patientProperty></patientProperty>
        <isEnabled>true</isEnabled>
        <ruleDefinitions/>
        <enumerations/>
        <shared>false</shared>
        <starSchemaName>treatment_other</starSchemaName>
        <encounterRecordproperty></encounterRecordproperty>
        <patientStatusproperty></patientStatusproperty>
      </form__field>
      <formFieldId>1383</formFieldId>
      <displayOrder>13</displayOrder>
      <inputType>checkbox</inputType>
      <closeRow>false</closeRow>
      <columnNumber>0</columnNumber>
      <size>0</size>
      <maxlength>0</maxlength>
      <rows>0</rows>
      <cols>0</cols>
      <visible>true</visible>
      <visibleEnumIdTrigger1>-1</visibleEnumIdTrigger1>
      <visibleDependencies1></visibleDependencies1>
      <visibleEnumIdTrigger2>-1</visibleEnumIdTrigger2>
      <selectedEnum>-1</selectedEnum>
      <visibleDependencies2></visibleDependencies2>
      <formId>37</formId>
      <colspan>0</colspan>
    </org.cidrz.webapp.dynasite.valueobject.PageItem>
    <org.cidrz.webapp.dynasite.valueobject.PageItem>
      <id>1860</id>
      <form__field>
        <id>818</id>
        <label>Treatment: Other, Descrbe</label>
        <type>Text</type>
        <required>false</required>
        <minValue>0</minValue>
        <maxValue>0</maxValue>
        <units></units>
        <displayOrder>2147483647</displayOrder>
        <patientProperty></patientProperty>
        <isEnabled>true</isEnabled>
        <ruleDefinitions/>
        <enumerations/>
        <shared>false</shared>
        <starSchemaName>treatment_other_desc_818</starSchemaName>
        <encounterRecordproperty></encounterRecordproperty>
        <patientStatusproperty></patientStatusproperty>
      </form__field>
      <formFieldId>818</formFieldId>
      <displayOrder>14</displayOrder>
      <inputType>textarea</inputType>
      <closeRow>false</closeRow>
      <columnNumber>0</columnNumber>
      <size>0</size>
      <maxlength>0</maxlength>
      <rows>0</rows>
      <cols>0</cols>
      <visible>true</visible>
      <visibleEnumIdTrigger1></visibleEnumIdTrigger1>
      <visibleDependencies1></visibleDependencies1>
      <visibleEnumIdTrigger2></visibleEnumIdTrigger2>
      <selectedEnum>0</selectedEnum>
      <visibleDependencies2></visibleDependencies2>
      <formId>37</formId>
      <colspan>0</colspan>
    </org.cidrz.webapp.dynasite.valueobject.PageItem>
    <org.cidrz.webapp.dynasite.valueobject.PageItem>
      <id>1861</id>
      <form__field>
        <id>1184</id>
        <label>Enter Antibiotics Used</label>
        <type>Text</type>
        <required>false</required>
        <minValue>0</minValue>
        <maxValue>0</maxValue>
        <units></units>
        <displayOrder>2147483647</displayOrder>
        <patientProperty></patientProperty>
        <isEnabled>true</isEnabled>
        <ruleDefinitions/>
        <enumerations/>
        <shared>false</shared>
        <starSchemaName>antibics_used_1184</starSchemaName>
        <encounterRecordproperty></encounterRecordproperty>
      </form__field>
      <formFieldId>1184</formFieldId>
      <displayOrder>15</displayOrder>
      <inputType>textarea</inputType>
      <closeRow>true</closeRow>
      <columnNumber>0</columnNumber>
      <size>0</size>
      <maxlength>0</maxlength>
      <rows>0</rows>
      <cols>0</cols>
      <visible>true</visible>
      <visibleEnumIdTrigger1></visibleEnumIdTrigger1>
      <visibleDependencies1></visibleDependencies1>
      <formId>37</formId>
      <colspan>2</colspan>
    </org.cidrz.webapp.dynasite.valueobject.PageItem>
    <org.cidrz.webapp.dynasite.valueobject.PageItem>
      <id>2781</id>
      <form__field>
        <id>1428</id>
        <label>END TABLE</label>
        <type>Display</type>
        <required>false</required>
        <minValue>0</minValue>
        <maxValue>0</maxValue>
        <units></units>
        <displayOrder>2147483647</displayOrder>
        <patientProperty></patientProperty>
        <isEnabled>true</isEnabled>
        <ruleDefinitions/>
        <enumerations/>
        <shared>true</shared>
        <starSchemaName></starSchemaName>
        <encounterRecordproperty></encounterRecordproperty>
      </form__field>
      <formFieldId>1428</formFieldId>
      <displayOrder>16</displayOrder>
      <inputType>display-tbl-end</inputType>
      <closeRow>false</closeRow>
      <columnNumber>0</columnNumber>
      <size>0</size>
      <maxlength>0</maxlength>
      <rows>0</rows>
      <cols>1</cols>
      <visible>true</visible>
      <formId>37</formId>
      <colspan>0</colspan>
    </org.cidrz.webapp.dynasite.valueobject.PageItem>
  </pageItems>
  <formfields class="tree-set">
    <comparator class="org.cidrz.webapp.dynasite.utils.sort.DisplayOrderComparator"/>
  </formfields>
  <submissions>0</submissions>
  <maxSubmissions>100</maxSubmissions>
</org.cidrz.webapp.dynasite.valueobject.Form>